boneio/__init__.py
boneio/bonecli.py
boneio/const.py
boneio/exceptions.py
boneio/runner.py
boneio/version.py
boneio/boards/0.2/input.yaml
boneio/boards/0.2/output_24_16.yaml
boneio/boards/0.2/output_32_10.yaml
boneio/boards/0.2/output_32_5.yaml
boneio/boards/0.2/output_cover.yaml
boneio/boards/0.2/output_cover_mix.yaml
boneio/boards/0.3/input.yaml
boneio/boards/0.3/output_24_16.yaml
boneio/boards/0.3/output_32_10.yaml
boneio/boards/0.3/output_32_5.yaml
boneio/boards/0.3/output_cover.yaml
boneio/boards/0.3/output_cover_mix.yaml
boneio/boards/0.4/input.yaml
boneio/boards/0.4/output_24_16.yaml
boneio/boards/0.4/output_32_10.yaml
boneio/boards/0.4/output_32_5.yaml
boneio/boards/0.4/output_cover.yaml
boneio/boards/0.4/output_cover_mix.yaml
boneio/boards/0.5/input.yaml
boneio/boards/0.5/output_24_16.yaml
boneio/boards/0.5/output_32_10.yaml
boneio/boards/0.5/output_cover.yaml
boneio/boards/0.5/output_cover_mix.yaml
boneio/boards/0.6/input.yaml
boneio/boards/0.6/output_24_16.yaml
boneio/boards/0.6/output_32_10.yaml
boneio/boards/0.6/output_cover.yaml
boneio/boards/0.6/output_cover_mix.yaml
boneio/boards/0.7/input.yaml
boneio/boards/0.7/output_24_16.yaml
boneio/boards/0.7/output_32_10.yaml
boneio/boards/0.7/output_cover.yaml
boneio/boards/0.7/output_cover_mix.yaml
boneio/boards/0.8/input.yaml
boneio/boards/0.8/output_24_16.yaml
boneio/boards/0.8/output_32_10.yaml
boneio/boards/0.8/output_cover.yaml
boneio/boards/0.8/output_cover_mix.yaml
boneio/components/__init__.py
boneio/components/cover/__init__.py
boneio/components/cover/cover.py
boneio/components/cover/previous.py
boneio/components/cover/time_based.py
boneio/components/cover/venetian.py
boneio/components/group/__init__.py
boneio/components/group/output_group.py
boneio/components/input/__init__.py
boneio/components/input/binary_sensor.py
boneio/components/input/detectors.py
boneio/components/input/event.py
boneio/components/output/__init__.py
boneio/components/output/basic.py
boneio/components/output/mcp.py
boneio-1.0.3.dist-info/licenses/LICENSE
boneio-1.0.3.dist-info/METADATA
boneio-1.0.3.dist-info/WHEEL
boneio-1.0.3.dist-info/entry_points.txt
boneio-1.0.3.dist-info/top_level.txt
boneio-1.0.3.dist-info/RECORD
